MANIFEST.in
README.md
pyproject.toml
requirements.txt
setup.cfg
src/__init__.py
src/light_chain.egg-info/PKG-INFO
src/light_chain.egg-info/SOURCES.txt
src/light_chain.egg-info/dependency_links.txt
src/light_chain.egg-info/requires.txt
src/light_chain.egg-info/top_level.txt
src/lightchain.egg-info/PKG-INFO
src/lightchain.egg-info/SOURCES.txt
src/lightchain.egg-info/dependency_links.txt
src/lightchain.egg-info/requires.txt
src/lightchain.egg-info/top_level.txt
src/litchain/__init__.py
src/litchain.egg-info/PKG-INFO
src/litchain.egg-info/SOURCES.txt
src/litchain.egg-info/dependency_links.txt
src/litchain.egg-info/requires.txt
src/litchain.egg-info/top_level.txt
src/litchain/llm/__init__.py
src/litchain/llm/_utils.py
src/litchain/llm/autogpt.py
src/litchain/llm/base_model.py
src/litchain/llm/llm_tool.py
src/litchain/llm/messages.py
tests/test_light_chain.py