Metadata-Version: 2.1
Name: litchain
Version: 0.0.2
Summary: litchain
Home-page: https://github.com/iuiu34/litchain
Author: iuiu
Author-email: iuiu@iuiu.com
License: COPYRIGHT
Keywords: litchain
Classifier: Development Status :: 2 - Pre-Alpha
Classifier: Programming Language :: Python :: 3 :: Only
Classifier: Programming Language :: Python :: 3.9
Requires-Dist: fire
Requires-Dist: openai>=1.2.4
